buffercache.py
buffercache-1.0.2.dist-info/LICENSE
buffercache-1.0.2.dist-info/METADATA
buffercache-1.0.2.dist-info/WHEEL
buffercache-1.0.2.dist-info/top_level.txt
buffercache-1.0.2.dist-info/RECORD
