Metadata-Version: 2.1
Name: buffercache
Version: 1.0.2
Summary: a tool for data caching
Home-page: https://github.com/caibingcheng/buffercache
Author: bbing
Author-email: jack_cbc@163.com
License: MIT
Platform: UNKNOWN
Requires-Python: >=3.0
License-File: LICENSE
